easyPyDB/__init__.py
easyPyDB/easyPythDB.py
easypythdb-0.1.0.dist-info/LICENSE
easypythdb-0.1.0.dist-info/METADATA
easypythdb-0.1.0.dist-info/WHEEL
easypythdb-0.1.0.dist-info/top_level.txt
easypythdb-0.1.0.dist-info/RECORD
