Metadata-Version: 2.1
Name: easypythdb
Version: 0.1.0
Summary: A super simple database manager with powerful features.
Home-page: https://github.com/twoj-uzytkownik/easypydb
Author: kserafin17
Author-email: twoj.email@example.com
Classifier: Programming Language :: Python :: 3
Classifier: License :: OSI Approved :: MIT License
Classifier: Operating System :: OS Independent
Requires-Python: >=3.6
License-File: LICENSE
